MANIFEST.in
setup.cfg
setup.py
BloodSpiderModel/__init__.py
BloodSpiderModel.egg-info/PKG-INFO
BloodSpiderModel.egg-info/SOURCES.txt
BloodSpiderModel.egg-info/dependency_links.txt
BloodSpiderModel.egg-info/requires.txt
BloodSpiderModel.egg-info/top_level.txt
BloodSpiderModel/BloodSpiderPrint/__init__.py
BloodSpiderModel/BloodSpiderPrint/custom_logger/__init__.py
BloodSpiderModel/BloodSpiderPrint/custom_logger/config.py
BloodSpiderModel/BloodSpiderPrint/custom_logger/example.py
BloodSpiderModel/BloodSpiderPrint/custom_logger/logger.py
BloodSpiderModel/DjangoResponseTool/__init__.py
BloodSpiderModel/DjangoResponseTool/response_dict.py
BloodSpiderModel/spider_tools/__init__.py
BloodSpiderModel/spider_tools/common_utils.py
BloodSpiderModel/spider_tools/file_operate.py
BloodSpiderModel/spider_tools/ua/__init__.py
BloodSpiderModel/spider_tools/ua/computer_ua.txt
BloodSpiderModel/spider_tools/ua/mobile_ua.txt
BloodSpiderModel/spider_tools/win_auto_gui/WindowAutoController.py
BloodSpiderModel/spider_tools/win_auto_gui/WindowAutoController文档.md
BloodSpiderModel/spider_tools/win_auto_gui/__init__.py
BloodSpiderModel/spider_tools/win_auto_gui/mouse_tracker.py
BloodSpiderModel/spider_tools/win_auto_gui/mouse_tracker_使用说明.md