Metadata-Version: 2.4
Name: BloodSpiderModel
Version: 1.0.19
Summary: BloodSpider系列必备的工具包!
Author: BloodSpider
Author-email: 18171759943@163.com
Keywords: python,bloodspider,spider,windows,mac,linux
Classifier: Development Status :: 4 - Beta
Classifier: Intended Audience :: Developers
Classifier: Programming Language :: Python :: 3
Classifier: Operating System :: Unix
Classifier: Operating System :: MacOS :: MacOS X
Classifier: Operating System :: Microsoft :: Windows
Requires-Dist: getch; platform_system == "Unix"
Requires-Dist: getch; platform_system == "Darwin"
Dynamic: author
Dynamic: author-email
Dynamic: classifier
Dynamic: description
Dynamic: description-content-type
Dynamic: keywords
Dynamic: requires-dist
Dynamic: summary
